setup.cfg
setup.py
travesty/__init__.py
travesty/base.py
travesty/datetypes.py
travesty/dispatch_graph.py
travesty/examples_and_notes.py
travesty/inference.py
travesty/invalid.py
travesty/list.py
travesty/mapping.py
travesty/object_marker.py
travesty/optional.py
travesty/passthrough.py
travesty/polymorph.py
travesty/schema.py
travesty/schema_obj.py
travesty/tuple.py
travesty/typed_leaf.py
travesty/validated.py
travesty/validators.py
travesty.egg-info/PKG-INFO
travesty.egg-info/SOURCES.txt
travesty.egg-info/dependency_links.txt
travesty.egg-info/requires.txt
travesty.egg-info/top_level.txt
travesty/cantrips/__init__.py
travesty/cantrips/dispatcher.py
travesty/cantrips/empty_instance.py
travesty/cantrips/error_aggregator.py
travesty/cantrips/has_cache.py
travesty/cantrips/immutable_dict.py
travesty/cantrips/subclass.py
travesty/document/__init__.py
travesty/document/docset.py
travesty/document/document.py