Metadata-Version: 1.1
Name: travesty
Version: 0.2.0
Summary: UNKNOWN
Home-page: https://github.com/dplepage/travesty
Author: Daniel Lepage
Author-email: dplepage@gmail.com
License: BSD
Platform: UNKNOWN
Classifier: Development Status :: 4 - Beta
Classifier: Programming Language :: Python :: 2
Classifier: Programming Language :: Python :: 3
